{"exception-reporting":{"userId":"2f54c8ac-8d76-475e-0410-a2e4ab104de2"},"release-notes":{"viewedVersion":"0.95.0"},"welcome":{"showOnStartup":false},"metrics":{"userId":"b7334f48c830f1c439fe3049b1083fd1de1a798d"},"editor":{"showIndentGuide":true,"showInvisibles":true},"core":{"disabledPackages":["Zen","vim-mode","autocomplete-plus","background-tips","linter","linter-coffeelint","linter-jshint","linter-scss-lint","atom-lint","linter-rubocop"],"projectHome":"/Users/mattgarrison/Projects"},"autosave":{"enabled":true},"autocomplete":{"includeCompletionsFromAllBuffers":true},"find-and-replace":{"openProjectFindResultsInRightPane":true},"autocomplete-plus":{"includeCompletionsFromAllBuffers":true,"liveCompletion":true},"spell-check":{},"test-status":{"Rakefile":"bundle exec rake test:all"},"zentabs":{"maximumOpenedTabs":8},"atom-lint":{"ignoredNames":["tmp/**"]},"rubocop":{"ignoredNames":["vendor/**","db/schema.rb"]},"linter":{"showStatusBarWhenCursorIsInErrorRange":true,"lintOnChangeInterval":2000},"linter-ruby":{},"linter-rubocop":{},"ruby-test":{"testAllCommand":"bundle exec ruby -I test test","testFileCommand":"bundle exec ruby -I test {relative_path}","testSingleCommand":"bundle exec ruby -I test {relative_path}:{line_number}","rspecAllCommand":"bundle exec rspec --tty spec","rspecFileCommand":"bundle exec rspec --tty {relative_path}","rspecSingleCommand":"bundle exec rspec --tty {relative_path}:{line_number}"}}